fundrives/__init__.py
fundrives/lanzou/__init__.py
fundrives/lanzou/core.py
fundrives/lanzou/extra.py
fundrives/lanzou/models.py
fundrives/lanzou/parser.py
fundrives/lanzou/types.py
fundrives/lanzou/utils.py
fundrive_lanzou-1.2.73.dist-info/METADATA
fundrive_lanzou-1.2.73.dist-info/WHEEL
fundrive_lanzou-1.2.73.dist-info/top_level.txt
fundrive_lanzou-1.2.73.dist-info/RECORD
