Metadata-Version: 2.4
Name: fundrive-lanzou
Version: 1.2.73
Summary: fundrive
Author-email: 牛哥 <niuliangtao@qq.com>, farfarfun <farfarfun@qq.com>
Maintainer-email: 牛哥 <niuliangtao@qq.com>, farfarfun <farfarfun@qq.com>
Project-URL: Organization, https://github.com/farfarfun
Project-URL: Repository, https://github.com/farfarfun/fundrive-lanzou
Project-URL: Releases, https://github.com/farfarfun/fundrive-lanzou/releases
Requires-Python: >=3.8
Requires-Dist: cryptography>=44.0.0
Requires-Dist: funutil>=1.0.43
